stagecoachml/__init__.py
stagecoachml/_base.py
stagecoachml/_validation.py
stagecoachml/classification.py
stagecoachml/py.typed
stagecoachml/regression.py
stagecoachml-0.2.0.dist-info/WHEEL
stagecoachml-0.2.0.dist-info/METADATA
stagecoachml-0.2.0.dist-info/RECORD
