Metadata-Version: 2.3
Name: stagecoachml
Version: 0.2.0
Summary: A library for two-stage machine learning models with staggered feature arrival
Keywords: machine learning,two-stage models,staged features,early prediction,residual learning,scikit-learn,multi-stage inference,feature arrival,latency optimization,progressive ml
Author: Gaurav Sood
Author-email: Gaurav Sood <contact@gsood.com>
License: MIT
Classifier: Development Status :: 3 - Alpha
Classifier: Intended Audience :: Developers
Classifier: Intended Audience :: Science/Research
Classifier: License :: OSI Approved :: MIT License
Classifier: Operating System :: OS Independent
Classifier: Programming Language :: Python :: 3
Classifier: Programming Language :: Python :: 3.11
Classifier: Programming Language :: Python :: 3.12
Classifier: Programming Language :: Python :: 3.13
Classifier: Topic :: Scientific/Engineering :: Artificial Intelligence
Classifier: Topic :: Software Development :: Libraries :: Python Modules
Classifier: Typing :: Typed
Requires-Dist: numpy>=1.20.0
Requires-Dist: pandas>=1.3.0
Requires-Dist: scikit-learn>=1.0.0
Requires-Dist: stagecoachml[dev,docs] ; extra == 'all'
Requires-Dist: pytest>=7.4.0 ; extra == 'dev'
Requires-Dist: pytest-cov>=4.1.0 ; extra == 'dev'
Requires-Dist: pytest-xdist>=3.5.0 ; extra == 'dev'
Requires-Dist: pytest-mock>=3.12.0 ; extra == 'dev'
Requires-Dist: hypothesis>=6.90.0 ; extra == 'dev'
Requires-Dist: ruff>=0.1.0 ; extra == 'dev'
Requires-Dist: mypy>=1.7.0 ; extra == 'dev'
Requires-Dist: pre-commit>=3.5.0 ; extra == 'dev'
Requires-Dist: types-pyyaml>=6.0.0 ; extra == 'dev'
Requires-Dist: pandas-stubs>=2.0.0 ; extra == 'dev'
Requires-Dist: sphinx>=7.2.0 ; extra == 'docs'
Requires-Dist: furo>=2023.9.10 ; extra == 'docs'
Requires-Dist: sphinx-autodoc-typehints>=1.25.0 ; extra == 'docs'
Requires-Dist: myst-nb>=1.0.0 ; extra == 'docs'
Requires-Dist: sphinx-copybutton>=0.5.2 ; extra == 'docs'
Requires-Dist: sphinx-design>=0.5.0 ; extra == 'docs'
Requires-Dist: jupyterlite-sphinx>=0.11.0 ; extra == 'docs'
Requires-Dist: jupyterlite-pyodide-kernel>=0.4.0 ; extra == 'docs'
Requires-Dist: jupyter>=1.0.0 ; extra == 'docs'
Maintainer: Gaurav Sood
Maintainer-email: Gaurav Sood <contact@gsood.com>
Requires-Python: >=3.11
Project-URL: Bug Tracker, https://github.com/finite-sample/stagecoachml/issues
Project-URL: Changelog, https://github.com/finite-sample/stagecoachml/blob/main/CHANGELOG.md
Project-URL: Documentation, https://finite-sample.github.io/stagecoachml/
Project-URL: Homepage, https://github.com/finite-sample/stagecoachml
Project-URL: Repository, https://github.com/finite-sample/stagecoachml
Provides-Extra: all
Provides-Extra: dev
Provides-Extra: docs
